{
  "id": "2026-07-07-nicolas-poussin-saints-peter-and-john-healing-the-lame-man",
  "date": "2026-07-07",
  "source": {
    "name": "The Met",
    "url": "https://www.metmuseum.org/art/collection/search/437330"
  },
  "originalTitle": "Saints Peter and John Healing the Lame Man — Nicolas Poussin",
  "image": "https://images.metmuseum.org/CRDImages/ep/web-large/DP340180.jpg",
  "category": "art",
  "art": {
    "artist": "Nicolas Poussin",
    "title": "Saints Peter and John Healing the Lame Man",
    "year": "1655",
    "medium": "Oil on canvas"
  },
  "languages": {
    "en": {
      "A1": {
        "title": "Healing a Man",
        "text": "This painting shows a scene. Two men help another man. He cannot walk. The colors are soft and calm. The sky is blue. The people wear bright clothes. They seem happy. The light shines on them. This makes the scene special. The men helping are important figures. They show kindness. This painting tells us about helping others. It is a good message.",
        "vocabulary": [
          {
            "word": "painting",
            "definition": "A picture made with colors."
          },
          {
            "word": "help",
            "definition": "To make something better or easier."
          },
          {
            "word": "walk",
            "definition": "To move by putting one foot in front of the other."
          },
          {
            "word": "colors",
            "definition": "Different shades like red, blue, or yellow."
          },
          {
            "word": "happy",
            "definition": "Feeling good or joyful."
          }
        ]
      },
      "A2": {
        "title": "Saints Peter and John Healing the Lame Man",
        "text": "In the painting, we see Saints Peter and John. They are helping a man who cannot walk. The scene is lively and full of people. Many colorful clothes fill the painting. The light shines on the figures. This makes them stand out. Saints Peter and John show kindness. They show compassion to the lame man. This act is very important. It shows the power of faith and healing. People in the painting look amazed. The mood is hopeful and bright. Poussin uses light and color very well. The background has nice buildings. This painting gives a message about helping those in need.",
        "vocabulary": [
          {
            "word": "saint",
            "definition": "A holy person in religion."
          },
          {
            "word": "healing",
            "definition": "Making someone better or healthy."
          },
          {
            "word": "compassion",
            "definition": "Feeling of sympathy for others."
          },
          {
            "word": "kindness",
            "definition": "Being nice and caring."
          },
          {
            "word": "bright",
            "definition": "Full of light or color."
          }
        ]
      },
      "B1": {
        "title": "The Healing of the Lame Man by Saints Peter and John",
        "text": "This painting by Nicolas Poussin shows a powerful moment. Saints Peter and John heal a lame man. He sits on the steps, unable to walk. The colors of the scene are rich and warm. Poussin uses light effectively. It creates a sense of divinity and hope. The people around the main figures express various reactions. Their faces show amazement and joy. This emphasizes the miraculous event. The composition is well organized. Figures are arranged in a semi-circle. There is a balance between the background and the foreground. This balance brings harmony to the painting. Poussin's focus on classical themes shows his admiration for order and clarity.",
        "vocabulary": [
          {
            "word": "powerful",
            "definition": "Strong and having great influence."
          },
          {
            "word": "miraculous",
            "definition": "Amazing and not usual."
          },
          {
            "word": "composition",
            "definition": "The way parts are arranged together."
          },
          {
            "word": "divinity",
            "definition": "The quality of being divine or god-like."
          },
          {
            "word": "admiration",
            "definition": "Respect and approval."
          }
        ]
      },
      "B2": {
        "title": "Nicolas Poussin's Saints Peter and John Healing the Lame Man",
        "text": "Nicolas Poussin's painting, 'Saints Peter and John Healing the Lame Man,' captures a poignant biblical moment. The central figures, Saints Peter and John, embody compassion as they extend help to a disabled man. Poussin employs a palette of warm hues, helping convey a sense of hope and renewal. The light sources in the painting highlight the emotional intensity of the scene. Each character's expression, from astonishment to joy, contributes to a unified narrative about faith and healing. The composition, characterized by its classical structure, offers a balance between architecture and human figures. Poussin's method reflects the Baroque interest in dramatic moments while maintaining a clear sense of order, typical of his style. This work showcases his belief in the power of art to communicate profound messages.",
        "vocabulary": [
          {
            "word": "poignant",
            "definition": "Causing a strong feeling of sadness or empathy."
          },
          {
            "word": "palette",
            "definition": "A range of colors used by an artist."
          },
          {
            "word": "renewal",
            "definition": "The act of making something new again."
          },
          {
            "word": "narrative",
            "definition": "A story or account of events."
          },
          {
            "word": "dramatic",
            "definition": "Relating to excitement and emotions."
          }
        ]
      },
      "C1": {
        "title": "The Theological Significance of Poussin's Healing Scene",
        "text": "Nicolas Poussin's 'Saints Peter and John Healing the Lame Man' serves not only as a visual representation of a biblical miracle but also as a rich commentary on faith, compassion, and the human condition. The painting is meticulously crafted, with an emphasis on clarity and order, hallmarks of Poussin's Baroque style. The use of light is particularly notable; sunlight streams down, illuminating the figures, enhancing their emotional gravitas. The reactions of the assembled crowd, ranging from awe to relief, highlight the transformative power of faith. By juxtaposing the divine figures of Peter and John with the incapacitated man, Poussin explores themes of healing and redemption. The architectural elements in the background ground the scene in a historical context, while the vibrant palette creates an inviting atmosphere. Poussin’s work resonates with classical ideals yet adheres to the emotional depth characteristic of Baroque art, making it a pivotal piece in art history.",
        "vocabulary": [
          {
            "word": "theological",
            "definition": "Relating to the study of religion."
          },
          {
            "word": "meticulously",
            "definition": "Showing great attention to detail."
          },
          {
            "word": "gravitas",
            "definition": "Seriousness or dignity in a situation."
          },
          {
            "word": "juxtaposing",
            "definition": "Placing two things side by side for comparison."
          },
          {
            "word": "redeeming",
            "definition": "Making something better or saving it."
          }
        ]
      },
      "C2": {
        "title": "Faith and Human Experience in Poussin's Masterpiece",
        "text": "Nicolas Poussin's 'Saints Peter and John Healing the Lame Man' transcends mere representation of biblical narrative, evolving into a profound exploration of faith, healing, and the interconnectedness of human experiences. Poussin intricately weaves together elements of light and shadow, creating a dynamic interplay that not only illuminates individual figures but also enhances the overarching theme of divine intervention. The painting's vivid color palette captures the emotional spectrum—joy, compassion, and astonishment—acting as a microcosm of human response to grace. The strategic placement of the figures within a classical architectural framework reinforces the significance of witnessing miracles against a backdrop of tradition and order. Poussin’s compositional strategy effectively channels the viewer’s gaze toward the act of healing, emphasizing its theological implications. This masterpiece invites contemplation on the transformative power of faith and the moral obligations it entails, resonating with viewers across time and context, thereby cementing its place in the canon of Western art history.",
        "vocabulary": [
          {
            "word": "transcends",
            "definition": "Goes beyond the usual limits."
          },
          {
            "word": "interconnectedness",
            "definition": "The way in which things are related to each other."
          },
          {
            "word": "dynamic interplay",
            "definition": "Active and changing interaction between elements."
          },
          {
            "word": "microcosm",
            "definition": "A small example of a larger system."
          },
          {
            "word": "theological implications",
            "definition": "The effects related to the study of religion or God."
          }
        ]
      }
    },
    "de": {
      "A1": {
        "title": "Heilung durch Petrus und Johannes",
        "text": "In diesem Bild hilft Petrus einem Mann. Der Mann sitzt auf der Treppe. Er hat ein verletztes Bein. Petrus schaut freundlich. Johannes steht neben ihm. Viele Menschen sind da. Sie beobachten die Heilung. Die Farben sind hell. Der Himmel ist blau. Das Licht ist warm. Die Szene ist wichtig. Sie zeigt Glauben und Hoffnung.",
        "vocabulary": [
          {
            "word": "Bild",
            "definition": "Ein Foto oder ein Gemälde."
          },
          {
            "word": "Hilfe",
            "definition": "Etwas, was man braucht."
          },
          {
            "word": "Mann",
            "definition": "Ein erwachsener Junge."
          },
          {
            "word": "sehen",
            "definition": "Mit den Augen wahrnehmen."
          },
          {
            "word": "freundlich",
            "definition": "nett und hilfsbereit."
          }
        ]
      },
      "A2": {
        "title": "Heilung des Lahmen",
        "text": "Das Bild zeigt Petrus und Johannes. Sie stehen vor vielen Menschen. Johannes hilft einem lahmen Mann. Der Mann sitzt auf der Treppe. Er sieht traurig aus. Petrus hat die Hand ausgestreckt. Er möchte helfen. Die Menschen schauen gespannt. Es gibt helle Farben. Der Himmel ist blau. Das Licht kommt von links. Es gibt große Säulen im Hintergrund. Diese Säulen machen das Bild stark und wichtig. Es geht um Glauben und Hoffnung. Die Menschen glauben an Wunder.",
        "vocabulary": [
          {
            "word": "zeigen",
            "definition": "sichtbar machen oder darstellen."
          },
          {
            "word": "traurig",
            "definition": "nicht glücklich sein."
          },
          {
            "word": "Hilfe",
            "definition": "Unterstützung oder Beistand."
          },
          {
            "word": "wichtig",
            "definition": "von großer Bedeutung."
          },
          {
            "word": "Säulen",
            "definition": "große, stabile Stützen."
          }
        ]
      },
      "B1": {
        "title": "Religiöse Heilung von Poussin",
        "text": "Das Gemälde von Nicolas Poussin zeigt Petrus und Johannes, die den lahmen Mann heilen. Die Szene spielt vor großen Säulen. Der Mann sitzt auf den Stufen. Er sieht hoffnungsvoll aus, während Petrus ihm die Hand reicht. Johannes steht neben ihm. Diese Handlung ist bedeutend, weil sie Glaube und Unterstützung zeigt. Die Farben sind sehr lebendig, und das Licht betont die Figuren. Poussins Wahl der Farben und das Licht schaffen eine positive Atmosphäre. Die Menschenbeobachter tragen verschiedene Gesichtsausdrücke. Das Bild zeigt die Wirkung von Glauben und Gemeinschaft. Poussin wollte die Bedeutung des Glaubens darstellen und das Wunder zeigen.",
        "vocabulary": [
          {
            "word": "Gemälde",
            "definition": "Ein bildliches Werk, oft mit Farben."
          },
          {
            "word": "Wunder",
            "definition": "etwas Erstaunliches oder Unglaubliches."
          },
          {
            "word": "Atmosphäre",
            "definition": "die Stimmung oder Umgebung."
          },
          {
            "word": "Hoffnung",
            "definition": "der Wunsch nach etwas Gutes."
          },
          {
            "word": "gemeinsam",
            "definition": "etwas mit anderen machen."
          }
        ]
      },
      "B2": {
        "title": "Poussins Darstellung von Glauben und Heilung",
        "text": "In \"Saints Peter and John Healing the Lame Man\" von Nicolas Poussin wird eine tiefgreifende religiöse Botschaft vermittelt. Das Bild, das im Jahr 1655 entstand, zeigt die entscheidende Heilung eines Lahmen durch die Apostel Petrus und Johannes. Die Komposition ist sorgfältig gestaltet, wobei große Säulen im Vordergrund eine monumentale Wirkung erzeugen. Das Licht fällt gezielt auf die Figuren, besonders auf den leidenden Mann, und verstärkt die emotionale Intensität der Szene. Poussin verwendet warme Farben, die ein Gefühl von Hoffnung und Glaube vermitteln. Die Zuschauer sind in verschiedenen Posen angeordnet, was die Dynamik der Handlung unterstreicht. Die Darstellung verweist auf die wichtigen Themen der Gemeinschaft und des Glaubens, die in der Barockzeit stark betont wurden. Poussin wollte mit dieser Komposition die Wunderkraft des Glaubens illustrieren und die Zuschauer zur Reflexion anregen.",
        "vocabulary": [
          {
            "word": "Botschaft",
            "definition": "eine wichtige Mitteilung oder Idee."
          },
          {
            "word": "heilen",
            "definition": "gesund machen oder reparieren."
          },
          {
            "word": "Komposition",
            "definition": "der Aufbau eines Bildes oder Werkes."
          },
          {
            "word": "Intensität",
            "definition": "Stärke oder Tiefe von Gefühlen."
          },
          {
            "word": "Thema",
            "definition": "ein zentrales Konzept oder Idee."
          }
        ]
      },
      "C1": {
        "title": "Religiöse Identität und Poussins künstlerische Entscheidungen",
        "text": "Nicolas Poussins \"Saints Peter and John Healing the Lame Man\" ist nicht nur ein Beispiel barocker Malerei, sondern auch eine tiefgründige Betrachtung von Glaubensfragen und menschlicher Existenz. Im Jahr 1655 geschaffen, zeigt das Werk die Momente, in denen Petrus und Johannes einen lahmen Mann heilen. Die dramatische Komposition wird von imposanten Säulen umrahmt, die den Raum sowohl spirituell als auch physisch strukturieren. Poussin setzt Licht und Schatten ein, um die Figuren zu definieren und Emotionen zu verstärken, insbesondere bei dem Mann, dessen Verletzung sowohl physische als auch metaphorische Bedeutung hat. Die Farbauswahl ist entscheidend: Lebhafte, warme Töne symbolisieren Hoffnung und Glauben, während die kühlen Farben der Umgebung die Isolation des Lahmen hervorheben. Diese visuelle Dualität spiegelt die (Barock-) Auseinandersetzung mit der Welt der Sinne und der spirituellen Überzeugungen wider. Poussin erhebt die Szenenwiedergabe zur Reflexion über Gemeinschaft, Glauben und das wahre Wesen von Wundern.",
        "vocabulary": [
          {
            "word": "Identität",
            "definition": "wer oder was jemand ist."
          },
          {
            "word": "dokumentieren",
            "definition": "festhalten oder aufzeichnen."
          },
          {
            "word": "Dualität",
            "definition": "Zwei Seiten oder Aspekte von etwas."
          },
          {
            "word": "spirituell",
            "definition": "das Religiöse oder Seelische betreffend."
          },
          {
            "word": "konzipieren",
            "definition": "etwas gestalten oder planen."
          }
        ]
      },
      "C2": {
        "title": "Poussins Meisterwerk: Reflexion von Glauben und menschlicher Erfahrung",
        "text": "Nicolas Poussins Gemälde „Saints Peter and John Healing the Lame Man“ aus dem Jahr 1655 ist ein Meisterwerk der Barockmalerei, das die Komplexität von Glauben, Gemeinschaft und menschlicher Schwäche thematisiert. Durch seine künstlerische Entscheidung, die Szene vor kolossalen Säulen darzustellen, schafft der Künstler eine eindrucksvolle Kulisse, die nicht nur den Raum definiert, sondern auch die Bedeutung der Heilung als zentrale Achse des Bildes hervorhebt. Das Spiel von Licht und Schatten ist meisterhaft inszeniert, wobei die helle Beleuchtung auf die Protagonisten gelenkt wird, während der lahme Mann im Zentrum sowohl Hoffnung als auch tiefes Leid verkörpert. Poussin verwendet eine Palette warmer Töne, um eine Atmosphäre des Glaubens zu schaffen, die den lahmen Mann umgibt, gleichzeitig jedoch die kalten, düsteren Farben der Zuschauerschaft betont, die ihre Distanz zum Geschehen aufzeigen. In der Barockzeit, in der Wunder und Spiritualität einen hohen Stellenwert hatten, vermittelt das Werk die Idee, dass echte Heilung sowohl körperlich als auch spirituell ist und regt zur Reflexion über die wahre Natur von Glauben und Gemeinschaft an. Poussins Gemälde ist damit nicht nur ein visuelles, sondern auch ein tief philosophisches Ereignis, das seine Zeit überdauert hat.",
        "vocabulary": [
          {
            "word": "Komplexität",
            "definition": "Vielschichtigkeit oder Schwierigkeit von etwas."
          },
          {
            "word": "Atmosphäre",
            "definition": "die Stimmung oder das Gefühl in einem Raum."
          },
          {
            "word": "veranschaulichen",
            "definition": "klar machen oder sichtbar darstellen."
          },
          {
            "word": "philosophisch",
            "definition": "die Lehre von den grundlegenden Gedanken und Ideen."
          },
          {
            "word": "überdauern",
            "definition": "lange bestehen bleiben, nicht enden."
          }
        ]
      }
    },
    "fr": {
      "A1": {
        "title": "Guérison de l'homme boiteux",
        "text": "Cette peinture montre Saint Pierre et Saint Jean. Ils guérissent un homme. L'homme est assis, il a besoin d'aide. Les couleurs sont vives. Les personnages sont habillés avec des robes colorées. La lumière tombe sur le groupe. Cela crée une atmosphère de bonté. On sent l'espoir. Les gens regardent avec attention. Ils sont surpris et admiratifs. C'est un moment spécial. La scène se passe devant des colonnes. Le fond est paisible. Cette œuvre est classique et belle.",
        "vocabulary": [
          {
            "word": "peinture",
            "definition": "une image sur une surface"
          },
          {
            "word": "montrer",
            "definition": "faire voir quelque chose"
          },
          {
            "word": "homme",
            "definition": "un être humain masculin"
          },
          {
            "word": "couleurs",
            "definition": "les teintes que nous voyons"
          },
          {
            "word": "lumière",
            "definition": "ce qui éclaire autour de nous"
          }
        ]
      },
      "A2": {
        "title": "La guérison dans la peinture",
        "text": "Cette peinture représente Saint Pierre et Saint Jean. Ils aident un homme boiteux. L'homme est assis sur les marches. Il semble triste et a besoin d'aide. Les couleurs de la peinture sont très vives. Les draps des personnages sont colorés et attirent l'œil. La lumière tombe sur eux, ce qui montre leur bonté. Les gens autour regardent avec admiration. Ils sont là pour voir le miracle. La scène est calme, mais remplie d'émotion. Le style est classique. Les détails comme les colonnes sont précis. Cela montre le talent de Poussin.",
        "vocabulary": [
          {
            "word": "représentent",
            "definition": "montrent une image"
          },
          {
            "word": "aident",
            "definition": "donner du soutien"
          },
          {
            "word": "triste",
            "definition": "ne pas être heureux"
          },
          {
            "word": "vives",
            "definition": "qui sont lumineuses"
          },
          {
            "word": "talent",
            "definition": "capacité spéciale"
          }
        ]
      },
      "B1": {
        "title": "Interprétation de la guérison",
        "text": "La peinture 'Saints Pierre et Jean guérissant l'homme boiteux' de Nicolas Poussin est très significative. Elle montre un moment de miracle. Dans cette scène, Saint Pierre touche l'homme, ce qui symbolise l'espoir et la foi. Les personnages sont vêtus de couleurs vives, ce qui attire l'œil du spectateur. La lumière éclaire principalement le groupe central, renforçant le sentiment de sacré. La composition, avec les colonnes qui encadrent la scène, donne une profondeur à l'œuvre. Poussin voulait transmettre un message de bonté et de rédemption. Il a utilisé des détails précis pour montrer la méticulosité de sa technique. En tant que représentant du baroque classique, il place l'homme au centre de l'émotion.",
        "vocabulary": [
          {
            "word": "significative",
            "definition": "qui a une grande importance"
          },
          {
            "word": "miracle",
            "definition": "un événement extraordinaire"
          },
          {
            "word": "symbole",
            "definition": "un signe qui représente quelque chose"
          },
          {
            "word": "sacré",
            "definition": "relatif à la religion"
          },
          {
            "word": "méthodique",
            "definition": "très organisé et précis"
          }
        ]
      },
      "B2": {
        "title": "Analyse de l'œuvre de Poussin",
        "text": "Nicolas Poussin, dans 'Saints Pierre et Jean guérissant l'homme boiteux', illustre un moment puissant de guérison et de sa compassion. Les figures, soigneusement disposées, révèlent une hiérarchie visuelle dirigée vers l'acte central de guérison. Les couleurs vives et contrastées attirent non seulement l'œil, mais évoquent également l'émotion sur la scène. La lumière, qui se concentre sur le groupe central, peut être vue comme un symbole de la grâce divine. Poussin favorise les lignes claires et une composition rationnelle pour incarner la perfection classique. En intégrant des éléments de la tradition baroque, il parvient à créer un équilibre entre le chaos émotionnel et l'ordre. Ce tableau, peint en 1655, dialogue avec les idéaux du classicisme, et insiste sur l'importance de la foi et de la communauté dans le contexte religieux.",
        "vocabulary": [
          {
            "word": "puissant",
            "definition": "très fort ou intense"
          },
          {
            "word": "compassion",
            "definition": "sentiment de sympathie pour les autres"
          },
          {
            "word": "hiérarchie",
            "definition": "ordre ou organisation de personnes ou choses"
          },
          {
            "word": "évoquer",
            "definition": "rappeler quelque chose à l'esprit"
          },
          {
            "word": "chaos",
            "definition": "grand désordre"
          }
        ]
      },
      "C1": {
        "title": "Signification et impact du chef-d'œuvre",
        "text": "L'œuvre 'Saints Pierre et Jean guérissant l'homme boiteux' de Nicolas Poussin est une illustration magistrale du style baroque français. Poussin capture non seulement l'essence de la guérison, mais il contextualise également cette action dans un moment d'intense humanité. Les figures, chacune avec leurs expressions distinctes, établissent une tension dramatique autour de l'événement central. La lumière, soigneusement orchestrée, souligne les traits des personnages, tandis que le choix des couleurs accentue la vitalité de la scène. Poussin, par son utilisation des lignes et des formes, crée une profondeur qui attire le spectateur dans l'expérience collective. Son retour à des thèmes classiques, particulièrement en 1655, reflète une quête pour la clarté et l'ordre face à l'émotion humaine. C'est une invitation à la réflexion sur la foi, la communauté, et le sens du sacré dans l'art et la vie.",
        "vocabulary": [
          {
            "word": "magistrale",
            "definition": "habile et impressionnant"
          },
          {
            "word": "contextualise",
            "definition": "placer dans un contexte spécifique"
          },
          {
            "word": "tension",
            "definition": "pression ou tension dans une situation"
          },
          {
            "word": "vitalité",
            "definition": "énergie et vie"
          },
          {
            "word": "quête",
            "definition": "recherche d'une chose"
          }
        ]
      },
      "C2": {
        "title": "Analyse approfondie du chef-d'œuvre de Poussin",
        "text": "Dans 'Saints Pierre et Jean guérissant l'homme boiteux', Nicolas Poussin transcende la simple représentation pour plonger dans une réflexion complexe sur la condition humaine. La scène, empreinte d'une lumineuse spiritualité, systématise la mitologie chrétienne au travers d'un acte de guérison qui va au-delà du visible. Ici, les couleurs, loin d’être simplement décoratives, s'avèrent être des vecteurs d'émotion, associant à chaque nuance un degré de sensibilité humaine. Les figures, figées dans cet instant de miracle, dévoilent des récits personnels autant que collectifs, illustrant l'interaction entre individualité et communauté. Poussin, en rehaussant les formes rigoureuses et en codifiant les expressions, nous invite à interroger notre propre rapport à la foi. À une époque où les tensions entre tradition et innovation sont palpables, cette oeuvre s'affirme comme un pivot du classicisme, réaffirmant la nécessité d'un dialogue entre l'art et la transcendance. Ainsi, elle reste un témoignage poignant de l'humanité, ancrée dans une quête éternelle dillumination et de compréhension spirituelle.",
        "vocabulary": [
          {
            "word": "transcende",
            "definition": "dépasser ou aller au-delà"
          },
          {
            "word": "empreinte",
            "definition": "marque laissée par quelque chose"
          },
          {
            "word": "vecteurs",
            "definition": "supports ou porteurs d'une idée"
          },
          {
            "word": "rigoureuses",
            "definition": "strictes et précises"
          },
          {
            "word": "palpables",
            "definition": "clairement visibles ou ressentis"
          }
        ]
      }
    },
    "tr": {
      "A1": {
        "title": "Kutsal Adamlar ve İyileştirme",
        "text": "Resim Kutsal Petrus ve Yuhanna’yı gösterir. İki adam, bir yalvarana yardım eder. Yalvaran, merhamet ister. Renkler canlı ve sıcak. İyileşme önemli bir durumdur. İnsanlar mutludur. Resim, sevgi ve yardımı anlatır. Sanatçı, resmi güzel yapar. Özellikle yüzler net görünür.",
        "vocabulary": [
          {
            "word": "ruh",
            "definition": "İnsanların içindeki duygular."
          },
          {
            "word": "yüz",
            "definition": "Başın ön kısmı."
          },
          {
            "word": "renk",
            "definition": "Görmek için gözle belirlenen şey."
          },
          {
            "word": "hayat",
            "definition": "Yapılan her şeyin toplamı."
          },
          {
            "word": "güzel",
            "definition": "Hoş ve çekici."
          }
        ]
      },
      "A2": {
        "title": "Kutsal Petrus ve Yuhanna'nın İyileştirmesi",
        "text": "Resimde, Kutsal Petrus ve Kutsal Yuhanna var. Bu adamlar, bir engelliye yardım ediyor. Engelli adam, merhamet istiyor. Renkler sıcak ve canlı. İnsanlar bir araya gelmiş. Birçok kişi görebiliriz. Resim, sevgi ve yardım etme duygularını gösteriyor. Petrus ve Yuhanna’nın yüzleri açıklayıcıdır. Tablodaki insanlar, iyilik yapmakta ısrar ediyor. Bu olay, Hristiyanlıkta önemlidir. Kutsal insanlar, başkalarına yardım eder.",
        "vocabulary": [
          {
            "word": "engelli",
            "definition": "Bir hareketi yapamayan kişi."
          },
          {
            "word": "merhamet",
            "definition": "Başka insanlara yardım duygusu."
          },
          {
            "word": "renk",
            "definition": "Görmek için farklılıktır."
          },
          {
            "word": "duygu",
            "definition": "İçsel his durumları."
          },
          {
            "word": "halk",
            "definition": "Bir araya gelen insanlar."
          }
        ]
      },
      "B1": {
        "title": "Kutsal Petrus ve Yuhanna'nın İyileştirmesi",
        "text": "Nicolas Poussin’in bu tablosu, Kutsal Petrus ve Kutsal Yuhanna’nın iyileştirme sahnesini gösteriyor. Tabloda engelli bir adam var. Adam, Petrus ve Yuhanna’ya yardım için yalvarıyor. Renkler sıcak ve tonları güzel. İnsanlar, merakla bu olaya bakıyor. Kutsal adamlar, başkalarını iyileştirmeyi seçiyor. Bu olay, Hristiyan inancında önemli bir anı temsil ediyor. Sanatçı, detayları ve yüz ifadelerini özenle göstermiş. İyilik ve sevgi, tablodaki en önemli temalardır. Ayrıca, Poussin’in tarzı, düzen ve netlik arayışını yansıtıyor.",
        "vocabulary": [
          {
            "word": "tablo",
            "definition": "Sanat eseri, resim."
          },
          {
            "word": "görüntü",
            "definition": "Bir şekil veya görünüş."
          },
          {
            "word": "tepki",
            "definition": "Bir şey karşısında duyulan his."
          },
          {
            "word": "temel",
            "definition": "Bir şeyin en önemli kısmı."
          },
          {
            "word": "seçim",
            "definition": "Bir şeyin tercih edilmesi."
          }
        ]
      },
      "B2": {
        "title": "Poussin’in Kutsal İyileştirmesi",
        "text": "Nicolas Poussin, 'Kutsal Petrus ve Yuhanna'nın İyileştirmesi' adlı tablosunda, dinî bir sahneyi ustaca ele alıyor. İşte burada, engelli bir adam, Kutsal iki figür olan Petrus ve Yuhanna’ya doğru uzanıyor. Renklerin sıcak tonları, sahnedeki duygusal yoğunluğu artırıyor. Poussin, kompozisyonda dikkatlice yerleştirilmiş detaylarla, izleyiciyi bu kutsal eylemin içine çekiyor. Işıklandırma, yüzlerdeki ifadeleri vurgularken, insan kalabalığı pozitif bir atmosfer yaratıyor. Tablodaki figürler, sevgi ve iyilik gibi derin temaları temsil ediyor. Bu eser, Barok döneminin dini içerikli anlatımlarını güçlü bir şekilde yansıtırken, aynı zamanda Poussin’in klasik üslubunu da göstermektedir. Bu tarz, daha sonraki sanatçılar üzerinde etkili olmuştur.",
        "vocabulary": [
          {
            "word": "ustaca",
            "definition": "Yetkin bir şekilde, çok iyi."
          },
          {
            "word": "figür",
            "definition": "Bir karakter veya insan resmi."
          },
          {
            "word": "atmosfer",
            "definition": "Bir ortamda hissedilen durum."
          },
          {
            "word": "içerik",
            "definition": "Bir şeyin öz veya anlamı."
          },
          {
            "word": "anlatım",
            "definition": "Bir konuyu ifade etme biçimi."
          }
        ]
      },
      "C1": {
        "title": "Poussin’in İyileştirici Teması",
        "text": "Nicolas Poussin’in 1655 tarihli 'Kutsal Petrus ve Yuhanna'nın İyileştirmesi', Barok tarzda bir dini anlatım sunuyor. Tablo, iki önemli figürün, Petrus ile Yuhanna'nın, bir engelli adamın iyileşmesi için gösterdikleri merhameti ön planda tutuyor. Renk paleti, sıcak ve çağrıcı tonlarla bezeli; bu, sahnenin duygusal etkisini artırıyor. Işık ve gölge, figürlerin ifadelerini netleştirmekte ve izleyicinin dikkatini çekmektedir. Poussin, kompozisyonda ustaca yerleştirilen figürlerle insan kalabalığını, insani değerleri temsil edecek şekilde tasarlamıştır. İyilik, toplumsal bağlılık ve dini inançlar, bu eserin ana temalarıdır. Aynı zamanda, sanatçının Barok dönemindeki klasik tarzı, sonraki sanatçılar için ilham kaynağı olmuştur. Kısaca, bu eser, hem sanatsal hem de spiritüel bir derinlik taşımaktadır.",
        "vocabulary": [
          {
            "word": "merhamet",
            "definition": "Başkalarına yardım etme isteği."
          },
          {
            "word": "ton",
            "definition": "Renk derecesi veya çeşidi."
          },
          {
            "word": "zengin",
            "definition": "Çok çeşit veya değerli."
          },
          {
            "word": "inanç",
            "definition": "Bir şeye güven ve kabul."
          },
          {
            "word": "bağlılık",
            "definition": "Bir şeye sadık olma durumu."
          }
        ]
      },
      "C2": {
        "title": "Poussin ve Kutsal İyileştirme Teması",
        "text": "Nicolas Poussin’in 1655 yılında ürettiği 'Kutsal Petrus ve Yuhanna'nın İyileştirmesi', sanatçıya özgü Barok üslubuyla dini semboller taşıyan bir eser olarak öne çıkmaktadır. Bu tabloda, Petrus ve Yuhanna'nın, acı çeken bir engelliye merhametle yaklaşmaları, insani değerlere ve yardımlaşma ruhuna işaret ediyor. Zengin renk paleti ve belirgin ışık kullanımı, sahnenin dramatik etkisini derinleştiriyor ve izleyicinin bakış açısını yönlendiriyor. Figürlerin düzeni, Poussin’in kompozisyon konusundaki ustalığını ortaya koyarken, aynı zamanda dönemin dini ve toplumsal bağlamını da gözler önüne seriyor. Engellinin çaresizliği, toplumun ihtiyacı olan destekle birleşiyor. Poussin, yapıtında bir yandan kutsallığı, diğer yandan da insanları kendi durumlarıyla yüzleştiren bir bakış açısı sunuyor. Bu eser, Barok sanatının inanç, özlem ve merhamet gibi derin temalarını gün yüzüne çıkarırken, sanatçının klasik anlayışının da modern yorumlarla birleştiğini gösteriyor.",
        "vocabulary": [
          {
            "word": "özgü",
            "definition": "Kendine has, benzersiz."
          },
          {
            "word": "sembol",
            "definition": "Bir şeyi temsil eden işaret."
          },
          {
            "word": "dramatik",
            "definition": "Etki gücü yüksek, çarpıcı."
          },
          {
            "word": "bağlam",
            "definition": "Bir şeyin bulunduğu durum veya çevre."
          },
          {
            "word": "yüzleşmek",
            "definition": "Bir durumla karşı karşıya gelmek."
          }
        ]
      }
    }
  }
}
