{
  "id": "2026-07-10-the-brothers-karamazov-fyodor-dostoevsky",
  "date": "2026-07-10",
  "source": {
    "name": "Wikipedia",
    "url": "https://en.wikipedia.org/wiki/The_Brothers_Karamazov"
  },
  "originalTitle": "The Brothers Karamazov (1880) — Fyodor Dostoevsky",
  "image": "https://covers.openlibrary.org/b/id/11263774-L.jpg",
  "category": "book",
  "book": {
    "author": "Fyodor Dostoevsky",
    "title": "The Brothers Karamazov",
    "year": "1880"
  },
  "languages": {
    "en": {
      "A1": {
        "title": "The Brothers Karamazov",
        "text": "The Brothers Karamazov is a big book. It is by Fyodor Dostoevsky. This book is about three brothers. They are very different from each other. The story happens in 19th-century Russia. The book starts with a big problem. The father of the brothers is not nice. He does many bad things. The brothers talk a lot about God and their choices. They think about right and wrong. They also argue about faith and doubt. Dostoevsky writes in a strong way. He has deep ideas in his writing. This book is very famous around the world. Many people love it. You can learn a lot from it. The brothers must face their father's actions. They have to search for truth and meaning in their lives.",
        "vocabulary": [
          {
            "word": "actions",
            "definition": "things someone does"
          },
          {
            "word": "choices",
            "definition": "decisions we make"
          },
          {
            "word": "different",
            "definition": "not the same"
          },
          {
            "word": "famous",
            "definition": "well known by many people"
          },
          {
            "word": "father",
            "definition": "male parent"
          },
          {
            "word": "write",
            "definition": "to form letters on a surface"
          },
          {
            "word": "world",
            "definition": "the earth and all people"
          }
        ]
      },
      "A2": {
        "title": "The Brothers Karamazov",
        "text": "The Brothers Karamazov is a famous novel by Fyodor Dostoevsky. It was published in 1880 and is his last work. The story takes place in 19th-century Russia, a time of great change. The book has three brothers: Dmitri, Ivan, and Alyosha. Each brother has a different personality and view of life. They discuss big ideas like God, free will, and morality. In the beginning, the brothers face a problem with their father, Fyodor Karamazov. He does not treat them well, which creates a lot of tension between them. Dostoevsky uses strong characters and rich emotions to show their struggles. Readers can see how life was changing in Russia at that time and how society affected the characters. The book invites you to think about important questions. These questions are still relevant today because they deal with faith and doubt. Reading this novel can help you understand human nature better. Many people still read it today. They want to explore the deep themes and complex characters in this important work. The Brothers Karamazov is a great story that continues to resonate with readers worldwide.",
        "vocabulary": [
          {
            "word": "patricide",
            "definition": "the act of killing one's father."
          },
          {
            "word": "theological",
            "definition": "related to the study of God and religious beliefs."
          },
          {
            "word": "philosophical",
            "definition": "related to the study of fundamental questions about existence, knowledge, and morality."
          },
          {
            "word": "morality",
            "definition": "principles concerning the difference between right and wrong."
          },
          {
            "word": "tension",
            "definition": "mental or emotional strain; a feeling of stress or worry."
          },
          {
            "word": "modernizing",
            "definition": "the process of adopting modern ideas, methods, or technology."
          },
          {
            "word": "characters",
            "definition": "the people or figures in a story."
          },
          {
            "word": "relevant",
            "definition": "closely connected or appropriate to what is being discussed."
          }
        ]
      },
      "B1": {
        "title": "The Brothers Karamazov",
        "text": "The Brothers Karamazov is a significant novel written by Fyodor Dostoevsky, first published in 1880. It is known as his final literary work, and Dostoevsky spent nearly two years writing it. Set in 19th-century Russia, the novel explores deep themes of faith, free will, and morality through the lives of three very different brothers: Dmitri, Ivan, and Alexei. Each brother has unique beliefs that reflect varied views on faith and the human condition.\n\nThe story begins with growing tensions between the brothers and their father, Fyodor Pavlovich, who is a morally corrupt and selfish man. This family conflict provides a dramatic backdrop for the philosophical discussions that follow. If readers pay attention, they will see how these conflicts push the brothers to question their own values and the nature of good and evil.\n\nDostoevsky’s unique voice is characterized by rich character development and thought-provoking questions. His exploration of moral dilemmas resonates with readers, showing how the characters’ struggles mirror many dilemmas we face in contemporary society. The novel invites us to think deeply about what it means to be human and the complexities of trust, love, and belief. Many readers and critics consider it a profound theological drama that deals with faith, doubt, and reason, especially as Russia itself was modernizing rapidly during this period. Because of its profound themes and masterful storytelling, The Brothers Karamazov continues to be celebrated as a classic in world literature. It has impacted many writers and thinkers who have come after Dostoevsky, shaping our understanding of moral philosophy and human psychology.",
        "vocabulary": [
          {
            "word": "patricide",
            "definition": "the act of killing one's father, often used in literature to explore family conflicts."
          },
          {
            "word": "theological",
            "definition": "relating to the study of God and religious beliefs."
          },
          {
            "word": "dilemma",
            "definition": "a situation where a difficult choice has to be made between two or more options."
          },
          {
            "word": "morality",
            "definition": "principles concerning the distinction between right and wrong or good and bad behavior."
          },
          {
            "word": "acclaimed",
            "definition": "publicly praised and recognized for something, usually in a positive way."
          },
          {
            "word": "resonate",
            "definition": "to have a strong emotional effect or to be meaningful to someone."
          },
          {
            "word": "philosophical",
            "definition": "related to the study of fundamental nature of knowledge, reality, and existence."
          },
          {
            "word": "modernizing",
            "definition": "making something more up-to-date or aligned with current practices and ideas."
          }
        ]
      },
      "B2": {
        "title": "The Brothers Karamazov",
        "text": "In 19th-century Russia, the complex and tumultuous lives of the Karamazov brothers reveal deep questions about existence, morality, and faith. The story begins with Fyodor Karamazov, a disreputable father whose troubled relationships with his three sons lay the groundwork for dramatic conflicts. Dmitri, the passionate eldest son, seeks love and meaning, often acting impulsively and allowing his emotions to dictate his decisions. In stark contrast, Ivan, the intellectual middle brother, grapples with existential doubts about God and morality, debating the merits of faith while expressing skepticism about divine justice. Meanwhile, Alyosha, the youngest brother, embodies compassion and faith; he strives to navigate the chaos of their family dynamic, offering a perspective of hope and redemption amidst turmoil.\n\nDostoevsky's rich narrative style delves into philosophical discussions, inviting readers to ponder concepts of free will and ethics. The novel is not merely a tale of family strife; it serves as a profound exploration of the human spirit’s struggles against doubt and despair. Characters frequently confront dilemmas that resonate with contemporary ethical questions. The exploration of themes such as patricide transforms the narrative into a theological drama that scrutinizes the balance between reason and belief within a rapidly modernizing Russia.\n\nHaving crafted this remarkable work over nearly two years, Dostoevsky's exploration of these existential themes continues to resonate deeply with readers today, making 'The Brothers Karamazov' an essential read for anyone interested in the complexities of human nature and the ongoing conflict between faith and reason. It challenges us to reflect on our own beliefs and values amid an ever-changing world, showcasing literature's power to provoke thought and inspire personal growth.",
        "vocabulary": [
          {
            "word": "patricide",
            "definition": "the act of killing one's father."
          },
          {
            "word": "existential",
            "definition": "relating to existence, particularly in relation to issues of life and meaning."
          },
          {
            "word": "theological",
            "definition": "relating to the study of God, religion, and the nature of religious belief."
          },
          {
            "word": "resonate",
            "definition": "to evoke a feeling of shared emotion or belief."
          },
          {
            "word": "dilemma",
            "definition": "a situation in which a difficult choice has to be made between two or more alternatives."
          },
          {
            "word": "contemporary",
            "definition": "existing or occurring in the present; modern."
          },
          {
            "word": "impulsively",
            "definition": "doing something suddenly without careful thought."
          },
          {
            "word": "turmoil",
            "definition": "a state of confusion or uncertainty."
          }
        ]
      },
      "C1": {
        "title": "The Brothers Karamazov",
        "text": "Regarded as one of the pinnacles of world literature, 'The Brothers Karamazov' by Fyodor Dostoevsky intricately examines profound philosophical questions through the lens of a turbulent family saga set against the backdrop of 19th-century Russia. The narrative centers around the Karamazov family, particularly the tumultuous relationships between the brothers—Dmitri's impulsive passion, Ivan's intellectual skepticism, and Alyosha's fervent faith coalesce to create a rich tapestry of conflicting ideologies and emotional turmoil. Dostoevsky does not merely recount events but invites readers to engage with pressing themes surrounding faith, freedom, and morality, highlighting the dialectic between belief and doubt that permeates human existence. \n\nMoreover, the existential dilemmas faced by these intricately crafted characters resonate deeply, mirroring contemporary struggles with identity and ethical quandaries. For instance, the moral conflicts that arise from choices surrounding love, betrayal, and justice compel readers to reflect on their own lives, thus elevating Dostoevsky's exploration beyond mere storytelling to a profound inquiry into the human condition.\n\nThis literary masterpiece has not only stood the test of time but has also become a vital part of discussions on ethics and existentialism, given that it encourages readers to contemplate the continuum of good and evil within themselves. Having composed the novel during a significant historical period—the modernization of Russia—Dostoevsky reflects society's turbulence, making his work an indispensable read that continuously illuminates the complexities of human existence and moral choices. Undoubtedly, 'The Brothers Karamazov' remains an enduring testament to the transformative power of literature, inviting generations to wrestle with the questions that define our lives.",
        "vocabulary": [
          {
            "word": "coalesce",
            "definition": "to come together to form one mass or whole."
          },
          {
            "word": "quandary",
            "definition": "a state of perplexity or uncertainty over what to do in a difficult situation."
          },
          {
            "word": "permeate",
            "definition": "to spread throughout something."
          },
          {
            "word": "vital",
            "definition": "absolutely necessary or important; essential."
          },
          {
            "word": "indeed",
            "definition": "used to emphasize a statement or response confirming something already suggested."
          },
          {
            "word": "turbulence",
            "definition": "conflict; confusion or disturbance in a situation."
          },
          {
            "word": "existentialism",
            "definition": "a philosophical theory emphasizing the existence of the individual as a free and responsible agent."
          },
          {
            "word": "testament",
            "definition": "a person's will or something that serves as a sign or evidence of a specified fact, event, or quality."
          }
        ]
      },
      "C2": {
        "title": "The Brothers Karamazov",
        "text": "Fyodor Dostoevsky's 'The Brothers Karamazov' emerges as a seminal work that intricately weaves together the existential and theological dilemmas of the human condition, epitomizing the philosophical undercurrents of 19th-century Russia. At its core lies the visceral exploration of faith, morality, and the paradox of free will, presented through the tumult of the Karamazov family—a microcosm reflecting the broader sociopolitical upheavals of the era. This was a time when Russia grappled with the vestiges of serfdom, and progressive ideas were beginning to enter the collective consciousness, igniting fervent discussions on ethics and societal norms.\n\nEach brother represents divergent paths: Dmitri's volatile pursuit of desire, Ivan's cerebral grappling with atheism, and Alyosha's profound yearning for spiritual truth, forming a rich dialectic that challenges the reader's understanding of good and evil. Dostoevsky’s innovative narrative structure prompts questions about the nature of existence itself, intertwining despair with hope in a formidable dialogue that seeks to unearth the essence of humanity. With every family interaction and philosophical debate, the text resonates with a deep sorrow that often feels inexorable, provoking an unsettling reflection on our own spiritual dilemmas.\n\nThis novel transcends its historical context, remaining eternally relevant as it interrogates the moral fabric of society and the individual's place within it. Dostoevsky's insight into the complexities of the human psyche invites us to engage with our own convictions, making 'The Brothers Karamazov' not merely a literary masterpiece but a philosophical treatise, an exploration that continues to resonate profoundly in contemporary discourse. The characters, wrought with internal conflicts and tragic flaws, serve as an enduring reminder of the timeless struggle between faith and doubt, revealing the intricate layers of our own existence.",
        "vocabulary": [
          {
            "word": "seminal",
            "definition": "providing a strong foundation for future development; original or influential."
          },
          {
            "word": "epitomizing",
            "definition": "serving as a perfect example of a particular quality or type."
          },
          {
            "word": "dialectic",
            "definition": "the art of investigating or discussing the truth of opinions; a conversation between opposing ideas."
          },
          {
            "word": "interrogate",
            "definition": "to ask questions formally or systematically, often to uncover information."
          },
          {
            "word": "sociopolitical",
            "definition": "relating to the interrelation of social and political factors."
          },
          {
            "word": "resonate",
            "definition": "to produce or be filled with a deep, full sound; to evoke a feeling of shared emotion or belief."
          },
          {
            "word": "visceral",
            "definition": "relating to deep, inward feelings rather than to the intellect."
          },
          {
            "word": "inexorable",
            "definition": "impossible to prevent or stop; relentless."
          }
        ]
      }
    },
    "de": {
      "A1": {
        "title": "Die Brüder Karamasow",
        "text": "Die Brüder Karamasow ist ein Buch von Dostojewski. Es ist das letzte Buch des Autors. Die Geschichte spielt in Russland im 19. Jahrhundert. Dostojewski schreibt über drei Brüder. Jeder Bruder ist sehr verschieden. Ein Bruder denkt viel über Gott nach. Ein anderer Bruder hat viele Gefühle und ist leidenschaftlich. Der dritte Bruder ist anders als die anderen. Die Brüder haben Probleme mit ihrem Vater. Die Themen sind sehr wichtig. Es geht um die Familie, Gott und Freiheit. Leser können viel über die menschliche Natur lernen. Die Geschichte ist spannend und schwer. Viele Menschen lesen es, weil sie Fragen über das Leben haben. Das Buch ist sehr berühmt und wichtig in der Literatur.",
        "vocabulary": [
          {
            "word": "Familie",
            "definition": "eine Gruppe von Menschen, die verwandt sind"
          },
          {
            "word": "Sohn",
            "definition": "ein männliches Kind der Eltern"
          },
          {
            "word": "Vater",
            "definition": "der männliche Elternteil"
          },
          {
            "word": "Freundschaft",
            "definition": "eine enge Beziehung zwischen Menschen"
          },
          {
            "word": "Glaube",
            "definition": "die Überzeugung an etwas, oft an Gott"
          },
          {
            "word": "Leidenschaft",
            "definition": "starke Gefühle für etwas oder jemanden"
          },
          {
            "word": "Geschichte",
            "definition": "die Erzählung oder Handlung in einem Buch"
          }
        ]
      },
      "A2": {
        "title": "Die Brüder Karamasow",
        "text": "Die Brüder Karamasow ist ein sehr wichtiges Buch von Fyodor Dostojewski. Es wurde 1880 veröffentlicht und ist sein letztes Werk. Die Geschichte spielt im 19. Jahrhundert in Russland, während einer Zeit großer Veränderungen. Es geht um drei Brüder: Dmitri, Ivan und Alexei. Jeder Bruder hat unterschiedliche Meinungen über Gott, das Leben und die Freiheit. Der älteste Bruder, Dmitri, hat große Probleme mit seinem Vater, dem Kapitän Karamasow. Diese Probleme führen zu vielen Konflikten. Die Geschichten zeigen wichtige Fragen über Glaube, Zweifel und Moral. Dostojewski erzählt leidenschaftlich und tiefgründig. Dieses Buch ist ein theologisches Drama, weil es den inneren Kampf der Menschen darstellt. Viele Leser finden die Fragen auch heute noch sehr wichtig. Sie sind relevant für unser modernes Leben. Deswegen gilt das Buch bis heute als bedeutend für die Literatur und die Philosophie. Der Autor diskutiert schwerwiegende Themen, die uns alle betreffen, wie das Verhältnis zu Gott und die Verantwortung für unsere Taten. Viele Menschen lesen das Buch mehrmals, weil man immer neue Antworten finden kann. Es ist also ein zeitloses Werk.",
        "vocabulary": [
          {
            "word": "Kapitän",
            "definition": "Ein Titel für einen Marine- oder Schiffsführer."
          },
          {
            "word": "Philosophie",
            "definition": "Die Lehre von Grundfragen des Lebens, Wissens, Seins und Denkens."
          },
          {
            "word": "Kampf",
            "definition": "Ein Streit oder Konflikt zwischen Menschen oder Ideen."
          },
          {
            "word": "Verantwortung",
            "definition": "Die Pflicht, für die eigenen Entscheidungen und Taten einzugehen."
          },
          {
            "word": "Glauben",
            "definition": "Der feste Überzeugung an etwas, oft an Gott."
          },
          {
            "word": "Zweifel",
            "definition": "Das Gefühl von Unsicherheit oder Misstrauen."
          },
          {
            "word": "Moral",
            "definition": "Die Prinzipien oder Regeln für richtiges Verhalten."
          }
        ]
      },
      "B1": {
        "title": "Die Brüder Karamasow",
        "text": "Die Brüder Karamasow ist ein bedeutendes Werk von Fyodor Dostojewski, das 1880 veröffentlicht wurde. Es ist das letzte und wohl wichtigste Buch des Autors. Die Handlung spielt im 19. Jahrhundert in Russland, einer Zeit, die durch gesellschaftliche Veränderungen und politische Umbrüche geprägt ist. Diese Veränderungen beeinflussen die verschiedenen Charaktere in der Geschichte, besonders die Familie Karamasow. Die drei Brüder, Alescha, Dmitri und Iwan, repräsentieren differente Sichtweisen auf das Leben, die Moral und den Glauben. Alescha, der jüngste Bruder, ist optimistisch und strebt nach dem Guten. Wenn er leidenschaftlich über den Glauben spricht, fasziniert er viele Menschen. Dmitri hingegen kämpft ständig mit seinen inneren Konflikten und äußeren Umständen, die oft zu Spannungen führen. Iwan, der intellektuelle Bruder, stellt die Existenz Gottes in Frage und diskutiert tiefgründige philosophische Fragen. \nDostojewski behandelt essentielle Themen wie den Freiheitswillen des Menschen und die ewige Suche nach Sinn und Wahrheit. Die tiefgründigen Dialoge und philosophischen Überlegungen machen das Buch zu einer spirituellen Reise. Oft gibt es Streitgespräche zwischen den Brüdern, die die Leser zum Nachdenken anregen. Es beschäftigt sich mit dem Kampf zwischen Glauben und Zweifel, was die Probleme noch relevanter erscheinen lässt. Viele Leser finden, dass die Fragen des Buches auch heute noch wichtig sind. Die Brillanz von Dostojewski zeigt sich nicht nur in seinem einzigartigen Stil, sondern auch in den faszinierenden Charakteren, die ihm Leben eingehaucht haben. Daher bleibt es ein zeitloser Klassiker der Literatur, der generationenübergreifend begeistert.",
        "vocabulary": [
          {
            "word": "Patriarchie",
            "definition": "Das ist eine Gesellschaftsform, in der Männer eine führende Rolle spielen und Frauen weniger Rechte haben."
          },
          {
            "word": "intellektuell",
            "definition": "Das beschreibt eine Person, die sehr gebildet ist oder gerne über komplexe Themen nachdenkt."
          },
          {
            "word": "philosophisch",
            "definition": "Das bezieht sich auf das Studium grundlegender Fragen über das Leben, das Sein und das Wissen."
          },
          {
            "word": "gesellschaftliche Veränderungen",
            "definition": "Das sind Änderungen im Zusammenleben der Menschen in einer Gesellschaft."
          },
          {
            "word": "Relevanz",
            "definition": "Das bedeutet, wie wichtig oder aktuell etwas ist."
          },
          {
            "word": "spirituell",
            "definition": "Das bezieht sich auf Dinge, die den Glauben oder das Seelenleben betreffen."
          },
          {
            "word": "konfliktgeladen",
            "definition": "Das beschreibt Situationen, in denen es viele Spannungen oder Auseinandersetzungen gibt."
          },
          {
            "word": "Freiheit",
            "definition": "Das beschreibt den Zustand, in dem man selbst entscheiden kann, was man tut."
          }
        ]
      },
      "B2": {
        "title": "Die Brüder Karamasow von Fjodor Dostojewski",
        "text": "In dem 1880 veröffentlichten Werk 'Die Brüder Karamasow' stellt Fjodor Dostojewski große Fragen der menschlichen Existenz. Die Geschichte spielt im 19. Jahrhundert in Russland, einer Zeit tiefgreifender sozialer und politischer Umwälzungen, und behandelt zentrale Themen wie Glauben, Moral und den freien Willen. In der Eröffnung sehen wir die komplizierte Beziehung zwischen den Brüdern Karamasow, deren Konflikte oft auf tiefere philosophische und existenzielle Streitfragen hindeuten. Obwohl sie sehr unterschiedliche Charaktere sind, sind ihre Schicksale untrennbar miteinander verbunden, was die Komplexität der menschlichen Beziehungen verdeutlicht. Jeder Bruder verkörpert verschiedene Aspekte des Glaubens und der Moral, was zu intensiven Diskussionen und Auseinandersetzungen führt.\n\nWährend die Charaktere ihre persönlichen Kämpfe und Zweifel durchleben, wird der Leser dazu angeregt, über das Wesen des Glaubens und die Herausforderungen des Lebens nachzudenken. Der Roman gilt als eines der größten Werke der Weltliteratur, da er nicht nur die psychologischen Dimensionen seiner Charaktere darstellt, sondern auch die sozialen und politischen Umwälzungen seiner Zeit im Blick hat. Darüber hinaus zeigt Dostojewski, wie die Probleme des Glaubens und der Zweifel auch in der heutigen Zeit relevant sind. Er gelingt es, den Leser mit seinen lebendigen Charakteren und den tiefgründigen Fragen, die sie stellen, in die Welt des 19. Jahrhunderts zu entführen. Die Themen des Romans sind zeitlos und regen zur Reflexion über das eigene Leben und die Werte an, die wir vertreten. Zusammenfassend zeigt Dostojewski in diesem Meisterwerk, dass die Suche nach Wahrheit und der Sinn des Lebens universell ist und auch zukünftige Generationen ansprechen wird.",
        "vocabulary": [
          {
            "word": "Umwälzungen",
            "definition": "große Veränderungen oder Umbrüche, insbesondere in politischer oder sozialer Hinsicht."
          },
          {
            "word": "patricide",
            "definition": "der Mord an einem Vater, oft als zentrales Motiv in literarischen Werken."
          },
          {
            "word": "erkunden",
            "definition": "sich mit etwas intensiv beschäftigen, um mehr darüber zu erfahren."
          },
          {
            "word": "voller Fragen",
            "definition": "reich an bedeutenden und tiefgründigen Themen oder Fragestellungen."
          },
          {
            "word": "verbinden",
            "definition": "eine Beziehung zwischen Dingen oder Personen herstellen oder betonen."
          },
          {
            "word": "intensiv",
            "definition": "sehr stark oder ausgeprägt; tiefgehend."
          },
          {
            "word": "Reflexion",
            "definition": "das Nachdenken oder Überlegen über etwas, besonders über eigene Gedanken oder Gefühle."
          },
          {
            "word": "Meisterwerk",
            "definition": "ein besonders herausragendes und gelungenes Werk in der Kunst oder Literatur."
          }
        ]
      },
      "C1": {
        "title": "Die Brüder Karamasow: Ein philosophisches Meisterwerk von Fjodor Dostojewski",
        "text": "Fjodor Dostojewskis 'Die Brüder Karamasow', 1880 veröffentlicht, gilt nicht nur als sein letztes Werk, sondern auch als eines der herausragendsten Romane der Weltliteratur. In einem Russland des 19. Jahrhunderts, geprägt von sozialen Umbrüchen und einem Konflikt zwischen traditionellen Werten und modernen Ideen, entfaltet sich eine komplexe Erzählung, die tief in philosophischen und theologischen Fragestellungen verwurzelt ist. Die Geschichte konzentriert sich auf die turbulenten Beziehungen der Brüder Karamasow, deren Auseinandersetzungen nicht nur mit persönlichen Konflikten, sondern auch mit grundlegenden ethischen Dilemmas verknüpft sind. Insbesondere thematisieren sie die drängenden Fragen von Glauben, Zweifel sowie moralischer Verantwortung.\n\nDie Charaktere fungieren hierbei als Stellvertreter ihrer Überzeugungen, jedoch sind sie gleichzeitig lebendige und vielschichtige Individuen. Diese Dualität zwingt den Leser dazu, über die vielschichtige Natur des Menschen und die existentielle Fragestellung des Schicksals nachzudenken. Dostojewski, der während des Schreibens der Erzählung in Staraya Russa lebte, nutzt seinen eindringlichen psychologischen Realismus nicht nur, um die inneren Kämpfe seiner Protagonisten nachzuvollziehen, sondern provoziert auch eine tiefergehende Reflexion über die grundlegenden Fragen des Seins.\n\nDas Werk erlangte auch posthum besondere Beachtung, da es Themen anspricht, die zeitlos und von universeller Relevanz sind. Im Kontext der rasanten gesellschaftlichen Veränderungen in Russland wird der patricide, das zentrale Verbrechen der Erzählung, zum Symbol für die Herausforderung, die die heraufziehende Moderne an die bestehende Ordnung stellt. Dies macht 'Die Brüder Karamasow' auch im 21. Jahrhundert zu einem bedeutenden Diskussionspunkt über den Sinn des Lebens und die Struktur der menschlichen Gesellschaft.",
        "vocabulary": [
          {
            "word": "patricide",
            "definition": "Vatermord; das Töten eines Vaters durch sein Kind, oft als zentrales Motiv in literarischen Werken verwendet."
          },
          {
            "word": "theologisch",
            "definition": "die Lehre von der Natur und dem Wesen Gottes sowie von religiösen Fragen und Glaubensüberzeugungen betreffend."
          },
          {
            "word": "existentiell",
            "definition": "die Existenz betreffend; oft verwendet, um Fragen des Lebenssinns und des menschlichen Daseins zu beschreiben."
          },
          {
            "word": "gesellschaftlich",
            "definition": "die Gesellschaft betreffend; häufig im Kontext von sozialen Strukturen und Veränderungen genutzt."
          },
          {
            "word": "universell",
            "definition": "überall und immer gültig; nicht nur spezifisch für einen bestimmten Kontext, sondern allgemein anwendbar."
          },
          {
            "word": "Dilemma",
            "definition": "eine schwierige Entscheidungssituation, in der eine Person zwischen zwei oder mehreren gleichwertigen Alternativen wählen muss."
          },
          {
            "word": "Kampf",
            "definition": "eine Auseinandersetzung oder ein innerer Konflikt, oft metaphorisch für persönliche oder moralische Herausforderungen."
          }
        ]
      },
      "C2": {
        "title": "Dostojewski's Meisterwerk 'Die Brüder Karamasow' als tiefgreifende Analyse des Menschlichen",
        "text": "Mit 'Die Brüder Karamasow', seinem letzten Meisterwerk, gelingt Fjodor Dostojewski eine bemerkenswerte Synthese aus philosophischen Fragestellungen und psychologischem Realismus, die noch bis heute für Leser von großer Relevanz ist. Die komplexe Struktur des Romans, die in einem sozial und religiös aufgeladenen Russland verortet ist, reflektiert nicht nur die innere Zerrissenheit seiner Protagonisten, sondern auch die universellen Fragen des Glaubens, der Moral und des freien Willens. Immer wieder stellt sich der Leser der Konfrontation mit den existentiellen Dilemmata, die die Figuren durchleben: Wie gestaltet sich die Beziehung zwischen individueller Freiheit und ethischer Verantwortung? Ist der Mensch von Natur aus gut oder böse? Der geschickte Einsatz von Dialogen und inneren Monologen gibt den Charakteren eine Stimme, lässt sie lebendig erscheinen und befähigt den Leser, sich in ihren inneren Konflikten wiederzufinden. Dabei nutzt Dostojewski nicht nur die narrative Freiheit, um seine psychologischen Einsichten und moralischen Überlegungen einfließen zu lassen, sondern fordert durch seine diskursive Schreibweise auch die Leser heraus, sich mit den eigenen Überzeugungen und Zweifel auseinanderzusetzen. In diesem Sinne ist 'Die Brüder Karamasow' nicht nur ein literarisches Werk, sondern eine philosophische Erkundung des Menschlichen, die zu einem dauerhaften Diskurs anregt und somit ihren Platz in der intellektuellen Tradition unbestreitbar einnimmt.",
        "vocabulary": [
          {
            "word": "Synthese",
            "definition": "Vereinigung unterschiedlicher Elemente zu einem Ganzen."
          },
          {
            "word": "psychologischen",
            "definition": "Etwas, das mit dem Verhalten und Denken von Menschen zu tun hat."
          },
          {
            "word": "existentiellen",
            "definition": "Bezieht sich auf grundlegende Fragen des Lebens."
          },
          {
            "word": "diskursive",
            "definition": "Etwas, das Diskussion fordert oder fördert."
          },
          {
            "word": "Relevanz",
            "definition": "Bedeutung oder Wichtigkeit für jemanden oder etwas."
          }
        ]
      }
    },
    "fr": {
      "A1": {
        "title": "Les Frères Karamazov",
        "text": "Les Frères Karamazov est un livre important. Il est écrit par un auteur russe très célèbre. Son nom est Fiodor Dostoïevski. Ce livre sort en mille huit cent quatre-vingts. Il est le dernier livre de Dostoïevski. L'histoire parle de trois frères. Ils ont un père qui est très mauvais. Les frères ont beaucoup de problèmes. Ils parlent souvent de Dieu et de leurs doutes. Les questions de vie sont très sérieuses. Dans le livre, les frères cherchent la vérité. L'action se passe dans la Russie du dix-neuvième siècle. La Russie change beaucoup pendant cette période. Les gens aiment ce livre parce qu'il pose des questions sur la foi et la morale. Les lecteurs trouvent que l'histoire est très touchante.",
        "vocabulary": [
          {
            "word": "important",
            "definition": "qui a une grande valeur"
          },
          {
            "word": "célébre",
            "definition": "qui est connu par beaucoup de gens"
          },
          {
            "word": "histoire",
            "definition": "un récit de faits ou d'événements"
          },
          {
            "word": "problèmes",
            "definition": "des choses difficiles à résoudre"
          },
          {
            "word": "vérité",
            "definition": "ce qui est réel ou correct"
          },
          {
            "word": "doutes",
            "definition": "des questions ou incertitudes"
          },
          {
            "word": "cherchent",
            "definition": "tâchent de trouver quelque chose"
          },
          {
            "word": "touchante",
            "definition": "qui fait réfléchir ou qui émeut"
          }
        ]
      },
      "A2": {
        "title": "Les Frères Karamazov",
        "text": "Les Frères Karamazov est un roman écrit par Fiodor Dostoïevski. Il est publié en 1880. Ce livre est son dernier, et Dostoïevski a travaillé presque deux ans sur ce projet. Le livre parle de trois frères : Dmitri, Ivan et Alexeï. Ils ont un père qui pose des problèmes. Leur père est un homme égoïste et immoral. Cela cause des conflits dans la famille. Les frères discutent de la vie, de Dieu et de la moralité. Cela se passe en Russie au dix-neuvième siècle, une période de grands changements. Dostoïevski montre des questions importantes comme la foi, le doute et la responsabilité. Les personnages vivent des conflits profonds et cherchent à comprendre leurs choix. Ce livre est très apprécié par beaucoup de lecteurs car les thèmes sont profonds et toujours d'actualité. Dostoïevski utilise des dialogues puissants pour exprimer les idées de ses personnages. Les discussions sur la liberté et la foi sont très inspirantes. C'est un roman qui invite à réfléchir sur la condition humaine. Beaucoup d'étudiants lisent ce livre parce qu'il est essentiel dans la littérature mondiale. Les Frères Karamazov reste un classique étudié dans les écoles et les universités.",
        "vocabulary": [
          {
            "word": "roman",
            "definition": "un livre fictif, une histoire écrite"
          },
          {
            "word": "frères",
            "definition": "des garçons ou des hommes qui ont les mêmes parents"
          },
          {
            "word": "morale",
            "definition": "l'ensemble des règles de bonne conduite dans la société"
          },
          {
            "word": "conflits",
            "definition": "des disputes ou des désaccords"
          },
          {
            "word": "foi",
            "definition": "la croyance en quelque chose, souvent en Dieu"
          },
          {
            "word": "égoïste",
            "definition": "une personne qui ne pense qu'à elle-même"
          },
          {
            "word": "destin",
            "definition": "le cours de la vie, souvent vu comme inévitable"
          },
          {
            "word": "littérature",
            "definition": "l'ensemble des œuvres écrites, comme des romans et des poèmes"
          }
        ]
      },
      "B1": {
        "title": "Les Frères Karamazov",
        "text": "Les Frères Karamazov est un roman de Fiodor Dostoïevski, publié en 1880. Ce livre est considéré comme une œuvre majeure dans la littérature et a été écrit dans un contexte spécifique, celui de la Russie du dix-neuvième siècle, qui a connu de grandes transformations. Dostoïevski, qui a passé près de deux ans à écrire ce roman, a commencé à le publier sous forme de feuilleton dans la revue Le Messager Russe. Ce format a permis d'atteindre un large public, car les lecteurs attendaient chaque nouvelle partie avec impatience. \n\nLe roman parle de trois frères, chacun avec une personnalité différente et des valeurs variées. Leur relation devient compliquée à cause de leur père, dont les comportements peuvent être considérés comme problématiques. Les tensions entre les frères, qui représentent des visions du monde opposées, soulèvent des questions sur la foi, la raison, et la nature humaine. Par exemple, certains personnages expriment des doutes sur l'existence de Dieu, ce qui entraîne des débats douloureux mais nécessaire entre eux. \n\nDostoïevski est connu pour son style engagé et réfléchi, et Les Frères Karamazov ne fait pas exception. Ce roman aborde des thèmes comme le bien et le mal, qui restent pertinents aujourd'hui. Si vous aimez les récits profonds et philosophiques, ce roman est pour vous. Le livre vous plonge dans des réflexions sur la moralité et la liberté, qui invitent à réfléchir à votre propre vie. La profondeur des personnages et leurs luttes intérieures rendent cette œuvre inoubliable, et si un lecteur se consacre à cette lecture, il peut découvrir des vérités sur lui-même et sur le monde.",
        "vocabulary": [
          {
            "word": "essentiel",
            "definition": "très important, indispensable."
          },
          {
            "word": "transformation",
            "definition": "changement significatif dans un système ou une situation."
          },
          {
            "word": "doute",
            "definition": "incertitude sur quelque chose."
          },
          {
            "word": "moralité",
            "definition": "ce qui concerne le bien et le mal."
          },
          {
            "word": "philosophique",
            "definition": "relatif à des réflexions profondes sur la vie."
          },
          {
            "word": "tension",
            "definition": "stress ou conflit entre des personnes."
          },
          {
            "word": "situation",
            "definition": "état dans lequel se trouve une personne ou un événement."
          },
          {
            "word": "engagé",
            "definition": "qui participe activement à un débat ou une cause."
          }
        ]
      },
      "B2": {
        "title": "Les Frères Karamazov",
        "text": "Dans le roman Les Frères Karamazov, publié pour la première fois en 1880, l'auteur russe Fyodor Dostoevsky explore des thèmes profonds tels que la foi, la morale et la nature humaine. L'histoire se déroule en Russie au XIXe siècle, une époque marquée par de nombreux bouleversements sociaux et politiques. Le pays, alors en pleine modernisation, était confronté à des tensions entre la tradition et le progrès, ce qui enrichit le contexte du récit. L'intrigue se concentre sur les relations tumultueuses entre trois frères: Dmitri, Ivan et Alexeï, qui représentent chacun des facettes différentes de l'existence humaine. Bien que l'intrigue tourne autour d'un crime familial, les questionnements philosophiques soulevés sont bien plus importants que l'action elle-même. En effet, les réflexions sur la responsabilité personnelle et le libre arbitre démontrent l'importance des choix individuels dans un monde en mutation. La complexité psychologique des personnages, leurs doutes et leurs croyances, devient alors un vecteur de réflexion sur la nature humaine. Il est à noter que ce roman est souvent considéré comme l'une des plus grandes œuvres de la littérature mondiale. Au-delà des réflexions sur la moralité, Dostoevsky aborde aussi des thèmes universels qui continuent de résonner aujourd'hui. Par exemple, sa réflexion sur la foi et le doute invite à s'interroger sur notre relation avec Dieu. L'écriture de Dostoevsky, riche et nuancée, nous entraîne dans les méandres de l'âme humaine et dans un dialogue intérieur intense. Son style, à la fois lyrique et incisif, stimule une réflexion profonde sur les valeurs et les conflits qui animent notre existence, illustrant parfaitement que parfois, il faut que des choix difficiles soient pris pour atteindre une compréhension plus élevée de notre humanité.",
        "vocabulary": [
          {
            "word": "bouleversements",
            "definition": "changements radicaux ou perturbations"
          },
          {
            "word": "patricide",
            "definition": "meurtre du père"
          },
          {
            "word": "résonner",
            "definition": "avoir un écho, être pertinent ou significatif"
          },
          {
            "word": "nuancé",
            "definition": "qui présente des subtilités, des détails complexes"
          },
          {
            "word": "dialogue intérieur",
            "definition": "réflexion personnelle ou conversation interne d'un personnage"
          },
          {
            "word": "tensions",
            "definition": "conflits ou pressions entre différentes forces"
          },
          {
            "word": "nature humaine",
            "definition": "caractéristiques fondamentales de l'être humain"
          },
          {
            "word": "modernisation",
            "definition": "processus de rendre quelque chose plus moderne"
          }
        ]
      },
      "C1": {
        "title": "Les Frères Karamazov",
        "text": "À travers Les Frères Karamazov, son ultime chef-d'œuvre publié en 1880, Fyodor Dostoevsky nous offre une réflexion profondément philosophique sur la condition humaine. Ce roman, qui se déroule dans le contexte tumultueux et changeant de la Russie du XIXe siècle, met en scène trois frères aux personnalités diamétralement opposées, chacun incarnant des visions distinctes de la foi, du libre arbitre et de la quête morale. Le récit, centré sur des thèmes aussi sombres que le parricide et les méandres de la culpabilité, aborde des questionnements essentiels : doit-on sacrifier la raison pour la foi? La moralité est-elle inhérente à l'homme ou dépend-elle de ses choix? La voix de Dostoevsky, empreinte de tension dramatique et d'une intensité psychologique rare, nous engage à interroger nos propres convictions face à la complexité de l'existence. Ainsi, ce roman ne se limite pas à une simple narration; il se positionne comme un véritable traité théologique, où chaque personnage devient un reflet de nos propres dilemmes éthiques et notre rapport au divin. De plus, le contexte historique de la Russie, marqué par l'émergence de nouvelles idées philosophiques et scientifiques, enrichit encore davantage le propos de l'auteur. Les tensions entre modernité et tradition, foi et scepticisme, trouvent un écho particulier dans les tribulations des Karamazov. Alors que le lecteur explore ces thématiques intemporelles, Les Frères Karamazov demeure résolument pertinent face aux enjeux contemporains de la morale et de la spiritualité, incitant chacun à scruter les profondeurs de son âme, avec la perpétuelle quête de sens qui caractérise la condition humaine.",
        "vocabulary": [
          {
            "word": "émergence",
            "definition": "processus par lequel quelque chose commence à exister ou à se manifester."
          },
          {
            "word": "tribulations",
            "definition": "épreuves ou difficultés rencontrées par un individu."
          },
          {
            "word": "scepticisme",
            "definition": "attitude de doute ou de méfiance vis-à-vis de certaines croyances ou idées."
          },
          {
            "word": "patricide",
            "definition": "acte de tuer son père, utilisé ici comme une métaphore des conflits familiaux et des tensions morales."
          },
          {
            "word": "dilemme",
            "definition": "situation dans laquelle un choix difficile doit être fait entre plusieurs options."
          },
          {
            "word": "théologique",
            "definition": "relatif à l'étude de la nature de Dieu et des questions religieuses."
          },
          {
            "word": "modernité",
            "definition": "situation caractérisée par des idées, des styles et des modes de pensée contemporains."
          },
          {
            "word": "marqué",
            "definition": "imprimé ou influencé de manière significative par quelque chose."
          }
        ]
      },
      "C2": {
        "title": "Les Frères Karamazov",
        "text": "Le roman Les Frères Karamazov, dernière œuvre monumentale de Fyodor Dostoevsky, incarne une exploration fulgurante des tensions entre foi, raison et éthique dans une Russie en pleine mutation à la fin du XIXe siècle. Par le biais d’une narration subtile et d’un style indéfectiblement introspectif, Dostoevsky met en lumière les conflits internes qui tourmentent ses protagonistes, surtout dans le cadre intense du parricide, qui sert de catalyseur à des réflexions plus vastes sur la réputation de l’humanité et les ramifications du libre arbitre. La structure narrative impeccable, oscillant entre dialogues fervents et longues digressions théologiques, invite à une immersion complète dans les tourments de l’âme humaine, exposant les contradictions inhérentes à nos choix moraux. Ces réflexions prennent une dimension encore plus poignante lorsque l’auteur interroge le concept de la souffrance, posant la question : pourquoi l’homme, en quête de sens, se complairait-il dans une douleur qui semble parfois inévitable? La prose riche et évocatrice de Dostoevsky, par son mélange d’ironie douloureuse et de pathos profond, séduit tout lecteur désireux d'approfondir les enjeux cruciaux de la condition humaine. Les personnages emblématiques, comme le irrésistible Ivan ou le dévoué Alyosha, incarnent des facettes divergentes de l'âme humaine, rendant l'œuvre non seulement un récit mais un véritable miroir de nos propres luttes intérieures. En somme, ce texte traverse les âges, car il interroge des questions éternelles qui résonnent toujours dans notre société moderne, et par son audace philosophique, il ne manquera pas de susciter une remise en question de nos propres certitudes, constituant ainsi un véritable chef-d'œuvre de la littérature universelle.",
        "vocabulary": [
          {
            "word": "patricide",
            "definition": "meurtre de son propre père."
          },
          {
            "word": "catalyseur",
            "definition": "élément déclencheur d'un événement ou d'un processus."
          },
          {
            "word": "tergiversation",
            "definition": "action de tergiverser, d'hésiter ou de procrastiner."
          },
          {
            "word": "facette",
            "definition": "une des multiples dimensions ou aspects d'une réalité."
          },
          {
            "word": "pathos",
            "definition": "énergie émotionnelle intense, souvent liée à la souffrance."
          },
          {
            "word": "inévitabilité",
            "definition": "caractère de ce qui ne peut être évité."
          },
          {
            "word": "résonance",
            "definition": "effet d'écho, d'impact sur une autre réalité."
          },
          {
            "word": "dialectique",
            "definition": "art du dialogue, méthode de raisonnement qui explore des contradictions."
          }
        ]
      }
    },
    "es": {
      "A1": {
        "title": "Los hermanos Karamazov",
        "text": "Los hermanos Karamazov es una novela famosa. Es de Fyodor Dostoevsky. La novela se publica en 1880. Dostoevsky escribe el libro en Rusia. La historia tiene tres hermanos. Cada hermano tiene una personalidad diferente. Ellos son importantes en la trama. La historia es intensa y profunda. Habla de temas grandes, como Dios y la moral. También habla de la libertad y la fe. Los personajes experimentan conflictos familiares. El padre tiene problemas con los hijos. Este conflicto es importante en la novela. El libro se publica como una serie. Por eso, muchos lectores lo esperan. La novela tiene un lugar grande en la literatura. Muchos los lectores creen que es una obra maestra.",
        "vocabulary": [
          {
            "word": "publicar",
            "definition": "hacer un libro disponible a otros"
          },
          {
            "word": "trama",
            "definition": "la secuencia de eventos en una historia"
          },
          {
            "word": "conflicto",
            "definition": "un problema entre personas"
          },
          {
            "word": "importante",
            "definition": "algo que tiene valor o significado"
          },
          {
            "word": "libertad",
            "definition": "la capacidad de hacer elecciones"
          },
          {
            "word": "título",
            "definition": "el nombre de un libro o obra"
          },
          {
            "word": "narrativa",
            "definition": "la forma en que se cuenta una historia"
          },
          {
            "word": "personaje",
            "definition": "una persona en una historia o libro"
          }
        ]
      },
      "A2": {
        "title": "Los hermanos Karamazov",
        "text": "Los hermanos Karamazov es un libro escrito por Fyodor Dostoevsky. Publicado en 1880, este libro es conocido en todo el mundo. La historia ocurre en Rusia, en el siglo diecinueve. Tres hermanos tienen diferentes personalidades y creen en cosas distintas. Dmitri es apasionado y emocional; Ivan es intelectual y crítico; y Aliocha es espiritual y compasivo. Ellos enfrentan problemas de familia, conflictos internos y cuestiones importantes como la fe y la moral. Este libro no solo es una novela, sino también un estudio profundo de la naturaleza humana. Dostoevsky trabaja temas profundos y hace preguntas sobre Dios y la libertad. La obra es un drama de la fe y la duda, con un fuerte enfoque en el sentido de la vida. Muchos piensan que es uno de los mejores libros de la literatura. Además, la influencia de Dostoevsky ha perdurado en el tiempo. Hoy en día, las preguntas del libro aún son relevantes y importantes. Las discusiones sobre el bien y el mal, la responsabilidad y el perdón afectan a las personas en el mundo actual. Por eso, estudiar este libro es essencial para entender la literatura y la filosofía modernas.",
        "vocabulary": [
          {
            "word": "personalidades",
            "definition": "Características que definen a una persona."
          },
          {
            "word": "pasional",
            "definition": "Que tiene mucha emoción o entusiasmo."
          },
          {
            "word": "intelectual",
            "definition": "Relativo a la inteligencia o al pensamiento."
          },
          {
            "word": "espiritual",
            "definition": "Relativo a lo que no es material; de la mente o el alma."
          },
          {
            "word": "conflictos",
            "definition": "Disputas o enfrentamientos entre personas."
          },
          {
            "word": "filosofía",
            "definition": "Estudio fundamental sobre la existencia, el conocimiento y la moral."
          },
          {
            "word": "influencia",
            "definition": "Efecto que una persona o cosa ejerce sobre otra."
          },
          {
            "word": "relevante",
            "definition": "Que tiene importancia o significado en un contexto."
          }
        ]
      },
      "B1": {
        "title": "Los hermanos Karamazov",
        "text": "Los hermanos Karamazov es una obra maestra escrita por Fyodor Dostoevsky y publicada en 1880. Esta novela tiene lugar en Rusia durante el siglo diecinueve, un periodo que se caracteriza por profundos cambios sociales y políticos. En la historia, encontramos a los tres hermanos Karamazov, cada uno con personalidades y creencias muy diferentes. Dmitri es impulsivo y apasionado, Ivan es intelectual y escéptico, y Alyosha es espiritual y bondadoso. Cada uno de ellos enfrenta desafíos familiares complejos que les hacen cuestionar su lugar en el mundo. A través de sus interacciones, Dostoevsky aborda temas fundamentales como la existencia de Dios y el libre albedrío.\n\nLa novela presenta un profundo dilema moral, especialmente en la relación con su padre, quien representa la corrupción. Si los hermanos logran resolver sus conflictos internos, podrían encontrar la paz. A lo largo de sus páginas, el autor nos lleva a explorar la naturaleza humana y nuestras decisiones en la vida. Con el pasar de los años, la influencia de esta obra ha sido innegable, ya que continúa provocando debates en la sociedad actual sobre la fe y la razón.\n\nLa fuerza de su mensaje y profundidad hacen que sea un libro atemporal y significativo. Si alguien está buscando entender la condición humana, Los hermanos Karamazov debería ser una de las lecturas más esenciales. Los dilemas y luchas de los personajes nos muestran que, aunque los problemas cambien, las preguntas sobre la moralidad y la existencia siempre permanecen actuales.",
        "vocabulary": [
          {
            "word": "patricidio",
            "definition": "el acto de matar a un padre"
          },
          {
            "word": "dilema",
            "definition": "una situación en la que hay que elegir entre dos opciones difíciles"
          },
          {
            "word": "corrupto",
            "definition": "alguien que no es honesto y que actúa de forma desleal por dinero o poder"
          },
          {
            "word": "espiritual",
            "definition": "relacionado con el alma o la fe"
          },
          {
            "word": "innegable",
            "definition": "algo que no se puede negar o rechazar"
          },
          {
            "word": "atrapar",
            "definition": "capturar a alguien, como una idea o un sentimiento"
          },
          {
            "word": "decisiones",
            "definition": "elecciones que se hacen entre diferentes posibilidades"
          },
          {
            "word": "meditar",
            "definition": "pensar profundamente sobre algo"
          }
        ]
      },
      "B2": {
        "title": "Los hermanos Karamazov: Un viaje filosófico profundo",
        "text": "Los hermanos Karamazov, la última y más ambiciosa novela de Dostoevsky, se sitúa en una Rusia del siglo XIX en la que las tensiones sociales y espirituales están en plena efervescencia. A menudo se considera que este periodo histórico fue crucial, ya que la sociedad rusa estaba comenzando a experimentar cambios significativos con la llegada de nuevas ideas sobre la libertad y la moralidad. La obra plantea interrogantes fundamentales sobre la existencia de Dios, la libertad, el sufrimiento humano y la naturaleza de la moralidad, lo que invita al lector a reflexionar sobre la condición humana y los dilemas que surgen de nuestras elecciones. A medida que la historia avanza, los hermanos Karamazov, cada uno con su propia personalidad y principios, se ven inmersos en una serie de conflictos familiares que trascienden lo individual y tocan cuestiones universales de gran relevancia. La narrativa está impregnada de un tono filosófico y dramático, donde las emociones humanas son exploradas con una profundidad inigualable, lo que logra que el lector empatice con los personajes. Es importante destacar que la voz del autor se siente intensa y apasionada, lo que hace que el lector se sumerja en el texto casi de inmediato. La novela no solo se considera una obra maestra de la literatura mundial, sino también una exploración del pensamiento teológico y moral que sigue resonando en la actualidad. A través de su complejo entramado narrativo y sus personajes bien desarrollados, Dostoevsky nos desafía a cuestionar nuestras propias creencias y convicciones, haciéndonos reflexionar sobre la dualidad del ser humano entre el bien y el mal. Este retrato detallado de la vida y las luchas de los Karamazov sumerge al lector en las profundas contradicciones de la naturaleza humana, planteando un análisis que, sin duda, continúa vigente en los debates filosóficos modernos. En efecto, su legado literario puede ser visto como un llamado a la introspección y al diálogo sobre nuestra existencia y moralidad en un mundo cambiante.",
        "vocabulary": [
          {
            "word": "efervescencia",
            "definition": "Estado de agitación o efusión; en este contexto, se refiere al intenso debate y cambio social."
          },
          {
            "word": "cuestionar",
            "definition": "Interrogar o poner en duda la validez o verdad de algo."
          },
          {
            "word": "patricidio",
            "definition": "El acto de matar al propio padre; en la novela, es un tema central."
          },
          {
            "word": "empatizar",
            "definition": "Identificarse con alguien o comprender sus sentimientos."
          },
          {
            "word": "legado",
            "definition": "Algo que se deja o se transmite a las generaciones futuras; la influencia perdurable de una obra."
          },
          {
            "word": "dualidad",
            "definition": "La existencia de dos elementos opuestos o contrastantes; en este caso, el bien y el mal."
          },
          {
            "word": "teológico",
            "definition": "Relativo a la teología, el estudio de la naturaleza de Dios y los temas religiosos."
          }
        ]
      },
      "C1": {
        "title": "Los hermanos Karamazov: Un dilema existencial en la ficción rusa",
        "text": "Escrita por Fyodor Dostoevsky entre 1879 y 1880, **Los hermanos Karamazov** se erige como el testamento literario del autor, abordando cuestiones filosóficas que, a pesar de haber sido planteadas en el contexto del siglo XIX, mantienen su relevancia en la actualidad. La obra gira en torno a la familia Karamazov, cuyas tensiones internas se convierten en el escenario perfecto para explorar ideas complejas acerca de la fe, la razón y el libre albedrío. En este sentido, el texto puede considerarse un espejo del tumultuoso proceso de modernización que Rusia experimentaba en esa época, donde los viejos dogmas religiosos comenzaban a ceder ante nuevas corrientes de pensamiento y escepticismo. \n\nLa estructura de la novela permite a Dostoevsky presentar múltiples voces, cada una de las cuales ofrece una perspectiva única sobre la moralidad y el sentido de la existencia. A través de un uso magistral de la narración, el autor logra tejer un entramado de dilemas éticos que invitan a la reflexión continua. Se destaca, en particular, el personaje de Ivan Karamazov, quien, al cuestionar la existencia de Dios frente al sufrimiento humano, plantea interrogantes que resuenan aún en el presente. En contraste, su hermano, Alyosha, representa una fe más activa y esperanzada, simbolizando así un diálogo profundo entre las creencias y dudas de los personajes.  \n\nCon una prosa rica y evocadora, Dostoevsky desafía al lector a confrontar sus propias convicciones mientras indaga en el abismo de la naturaleza humana. Cada capítulo se transforma en una exploración intensamente humanista donde la angustia y las preguntas sobre el ser humano se encuentran en el centro del relato. El impacto de **Los hermanos Karamazov** trasciende las barreras temporales, invitando a nuevas generaciones a afrontar dilemas universales que permanecen vigentes en el contexto actual.",
        "vocabulary": [
          {
            "word": "trastornar",
            "definition": "alterar el orden natural o normal de algo."
          },
          {
            "word": "oponente",
            "definition": "persona que se muestra contraria a alguien o algo."
          },
          {
            "word": "credo",
            "definition": "sistema de creencias o principios, especialmente en un contexto religioso."
          },
          {
            "word": "inconmensurable",
            "definition": "que no se puede medir; ilimitado en su extensión o en su impacto."
          },
          {
            "word": "escepticismo",
            "definition": "afirmación de que el conocimiento verdadero es inaccesible."
          },
          {
            "word": "transgresor",
            "definition": "que infringe una norma o ley."
          },
          {
            "word": "dilema",
            "definition": "situación que requiere elegir entre dos o más opciones contradictorias."
          },
          {
            "word": "consternar",
            "definition": "causar gran inquietud o preocupación."
          }
        ]
      },
      "C2": {
        "title": "Los hermanos Karamazov: Una odisea filosófica de la existencia",
        "text": "Los hermanos Karamazov no solo es una narrativa compleja sobre los conflictos íntimos de una familia en la Rusia decimonónica; es un examen penetrante y polémico de las verdades universales que han desafiado a la humanidad desde tiempos inmemoriales. Dostoevsky, con un dominio absoluto del lenguaje y una arquitectura narrativa intrincada, coloca en el centro de su obra cuestiones que trascienden épocas y contextos, tales como la existencia de Dios, el valor del libre albedrío, y la naturaleza del bien y del mal. La obra, escrita en un periodo de cambio vertiginoso, refleja la profunda crisis espiritual que enfrentaba Rusia, entrelazando el drama familiar con una meditación filosófica que profundiza en la fragilidad de la vida humana. Cada personaje se convierte en un vehículo de dilemas morales que, en su búsqueda incesante de respuestas, pone de manifiesto las contradicciones inherentes a la condición humana. A través de diálogos vibrantes y una prosa estilísticamente refinada, Dostoevsky no solo invita al lector a cuestionar sus propias convicciones, sino que también plantea un desafío ético que resuena a lo largo de los siglos. Este espléndido y complejo texto sigue siendo pertinente, invitando a nuevas generaciones a sumergirse en las profundidades del alma humana.",
        "vocabulary": [
          {
            "word": "odisea",
            "definition": "un largo y complicado viaje o experiencia llena de cambios."
          },
          {
            "word": "penetrante",
            "definition": "que entra o afecta profundamente."
          },
          {
            "word": "contradicciones",
            "definition": "situaciones o afirmaciones opuestas que no pueden existir juntas."
          },
          {
            "word": "inherentes",
            "definition": "que son parte esencial de algo."
          },
          {
            "word": "vibrantes",
            "definition": "lleno de energía o emoción."
          }
        ]
      }
    }
  }
}
